Jenkinsfile
LICENSE
MANIFEST.in
Makefile
README.md
build.parameters
mypy.ini
pyproject.toml
setup.cfg
shortauthstrings.spec
tox.ini
src/shortauthstrings/__init__.py
src/shortauthstrings/py.typed
src/shortauthstrings.egg-info/PKG-INFO
src/shortauthstrings.egg-info/SOURCES.txt
src/shortauthstrings.egg-info/dependency_links.txt
src/shortauthstrings.egg-info/top_level.txt
tests/conftest.py
tests/test_package.py